README.md
setup.cfg
setup.py
modutils/__init__.py
modutils/aio.py
modutils/decorators.py
modutils/http.py
modutils.egg-info/PKG-INFO
modutils.egg-info/SOURCES.txt
modutils.egg-info/dependency_links.txt
modutils.egg-info/requires.txt
modutils.egg-info/top_level.txt