Metadata-Version: 2.1
Name: modutils
Version: 0.1.9
Summary: A library with modern utilities to assist development efficiency 
Home-page: https://www.github.com/tannerburns/modutils
Author: Tanner Burns
Author-email: tjburns102@gmail.com
License: UNKNOWN
Platform: UNKNOWN
Classifier: Operating System :: OS Independent
Classifier: Programming Language :: Python :: 3.7
